[{"_ent":"_cols","id":"_ents-_ent","ent":"_ents","name":"_ent","type":"ref","ref":"_ents","meta":"strong","label":"_ents-_ent"},{"_ent":"_cols","id":"_ents-id","ent":"_ents","name":"id","type":"string","meta":"strong","label":"_ents-id"},{"_ent":"_ents","id":"_ents","meta":"strong","updatedAt":"2024-11-10T00:07:36.437Z","singular":"Entity","plural":"Entities"},{"_ent":"_cols","id":"_cols-_ent","ent":"_cols","name":"_ent","type":"ref","ref":"_ents","meta":"strong","label":"_cols-_ent"},{"_ent":"_cols","id":"_cols-id","ent":"_cols","name":"id","type":"string","meta":"strong","label":"_cols-id"},{"_ent":"_ents","id":"_cols","meta":"strong","updatedAt":"2024-11-10T00:07:36.437Z","singular":"_cols","plural":"_cols"},{"_ent":"_cols","id":"_types-_ent","ent":"_types","name":"_ent","type":"ref","ref":"_ents","meta":"strong","label":"_types-_ent"},{"_ent":"_cols","id":"_types-id","ent":"_types","name":"id","type":"string","meta":"strong","label":"_types-id"},{"_ent":"_ents","id":"_types","meta":"strong","updatedAt":"2024-11-10T00:07:36.437Z","singular":"_types","plural":"_types"},{"_ent":"_types","id":"meta","meta":"strong"},{"_ent":"_types","id":"string","meta":"strong"},{"_ent":"_types","id":"boolean","meta":"strong"},{"_ent":"_types","id":"number","meta":"strong"},{"_ent":"_types","id":"datetime","meta":"strong"},{"_ent":"_types","id":"duration","meta":"strong"},{"_ent":"_types","id":"function","meta":"strong"},{"_ent":"_types","id":"object","meta":"strong"},{"_ent":"_types","id":"ref","meta":"strong"},{"_ent":"_types","id":"nref","meta":"strong"},{"_ent":"_types","id":"any","meta":"strong"},{"_ent":"_cols","id":"_ents-meta","meta":"strong","ent":"_ents","name":"meta","type":"meta","label":"_ents-meta"},{"_ent":"_cols","id":"_ents-cols","meta":"strong","ent":"_ents","name":"cols","type":"nref","ref":"_cols","parent":"_cols-ent","noCache":true,"label":"_ents-cols"},{"_ent":"_cols","id":"_types-meta","meta":"strong","ent":"_types","name":"meta","type":"meta","label":"_types-meta"},{"_ent":"_cols","id":"_types-setter","meta":"strong","ent":"_types","name":"setter","type":"function","label":"_types-setter"},{"_ent":"_cols","id":"_types-getter","meta":"strong","ent":"_types","name":"getter","type":"function","label":"_types-getter"},{"_ent":"_cols","id":"_cols-meta","meta":"strong","ent":"_cols","name":"meta","type":"meta","label":"_cols-meta"},{"_ent":"_cols","id":"_cols-ent","meta":"strong","ent":"_cols","name":"ent","type":"ref","ref":"_ents","label":"_cols-ent"},{"_ent":"_cols","id":"_cols-name","meta":"strong","ent":"_cols","name":"name","type":"string","label":"_cols-name"},{"_ent":"_cols","id":"_cols-type","meta":"strong","ent":"_cols","name":"type","type":"ref","ref":"_types","label":"_cols-type"},{"_ent":"_cols","id":"_cols-ref","meta":"strong","ent":"_cols","name":"ref","type":"ref","ref":"_ents","label":"_cols-ref"},{"_ent":"_cols","id":"_cols-parent","meta":"strong","ent":"_cols","name":"parent","type":"ref","ref":"_cols","label":"_cols-parent"},{"_ent":"_cols","id":"_cols-isList","meta":"strong","ent":"_cols","name":"isList","type":"boolean","label":"_cols-isList"},{"_ent":"_cols","id":"_cols-isReadonly","meta":"strong","ent":"_cols","name":"isReadonly","type":"function","label":"_cols-isReadonly"},{"_ent":"_cols","id":"_cols-isRequired","meta":"strong","ent":"_cols","name":"isRequired","type":"function","label":"_cols-isRequired"},{"_ent":"_cols","id":"_cols-resetIf","meta":"strong","ent":"_cols","name":"resetIf","type":"function","label":"_cols-resetIf"},{"_ent":"_cols","id":"_cols-init","meta":"strong","ent":"_cols","name":"init","type":"function","label":"_cols-init"},{"_ent":"_cols","id":"_cols-fallback","meta":"strong","ent":"_cols","name":"fallback","type":"function","label":"_cols-fallback"},{"_ent":"_cols","id":"_cols-validator","meta":"strong","ent":"_cols","name":"validator","type":"function","label":"_cols-validator"},{"_ent":"_cols","id":"_cols-decimal","meta":"strong","ent":"_cols","name":"decimal","type":"number","decimal":0,"min":0,"label":"_cols-decimal"},{"_ent":"_cols","id":"_cols-min","meta":"strong","ent":"_cols","name":"min","type":"number","label":"_cols-min"},{"_ent":"_cols","id":"_cols-max","meta":"strong","ent":"_cols","name":"max","type":"number","label":"_cols-max"},{"_ent":"_cols","id":"_cols-formula","meta":"strong","ent":"_cols","name":"formula","type":"function","label":"_cols-formula"},{"_ent":"_cols","id":"_cols-noCache","meta":"strong","ent":"_cols","name":"noCache","type":"boolean","label":"_cols-noCache"},{"_ent":"_cols","id":"_cols-omitChange","meta":"strong","ent":"_cols","name":"omitChange","type":"boolean","label":"_cols-omitChange"},{"_ent":"_cols","ent":"_cols","name":"label","type":"string","id":"_cols-label","label":"Štítek","fallback":"r=>r.id"},{"_ent":"_ents","id":"foo","updatedAt":"2024-11-10T00:07:36.440Z","singular":"foo","plural":"foo"},{"_ent":"_cols","id":"foo-_ent","ent":"foo","name":"_ent","type":"ref","ref":"_ents","isReadonly":"_=>true","isRequired":"_=>true","label":"foo-_ent"},{"_ent":"_cols","id":"foo-id","ent":"foo","name":"id","type":"string","isReadonly":"_=>true","isRequired":"_=>true","label":"foo-id"},{"_ent":"foo","id":"bar","list":["_ents","_cols","_types"]},{"_ent":"_cols","ent":"_ents","name":"updatedAt","id":"_ents-updatedAt","type":"datetime","omitChange":true,"resetIf":"_2=>true","init":"_=>new Date()","label":"_ents-updatedAt"},{"_ent":"_cols","ent":"_ents","name":"createdAt","id":"_ents-createdAt","type":"datetime","label":"_ents-createdAt"},{"_ent":"_cols","ent":"_ents","name":"singular","type":"string","id":"_ents-singular","label":"_ents-singular"},{"_ent":"_cols","ent":"_ents","name":"plural","type":"string","id":"_ents-plural","label":"_ents-plural"},{"_ent":"_cols","ent":"foo","name":"list","type":"ref","isList":true,"id":"foo-list","label":"foo-list","ref":"_ents"}]
